{
  "_comment": "MCP whitelist config \u2014 edit here to add/remove tools or methods. Auto-loaded at runtime.",
  "_managed_by": "mcp-manager skill (skills/mcp-manager/SKILL.md)",
  "allowed_methods": [
    "initialize",
    "tools/list",
    "tools/call",
    "ping",
    "notifications/initialized"
  ],
  "allowed_tools": [
    {
      "name": "search_skills",
      "rest_action": "search",
      "description": "Search 60,000+ AI agent skills by keyword or natural language",
      "status": "active"
    },
    {
      "name": "get_skill",
      "rest_action": "get",
      "description": "Fetch complete details for a single skill by slug",
      "status": "active"
    },
    {
      "name": "popular_skills",
      "rest_action": "popular",
      "description": "Get most-downloaded AI agent skills ranked by download count",
      "status": "active"
    },
    {
      "name": "search_use_cases",
      "rest_action": "use_cases",
      "description": "Search 342 real-world AI use-cases by task or goal",
      "status": "active"
    },
    {
      "name": "get_workflow",
      "rest_action": "workflow",
      "description": "Return a complete AI agent workflow with tested skill-stack candidates and upgrade path",
      "status": "active"
    },
    {
      "name": "submit_request",
      "rest_action": "submit_request",
      "description": "Submit a new skill request to the community wall.",
      "status": "active"
    },
    {
      "name": "list_requests",
      "rest_action": "list_requests",
      "description": "Get recent skill requests from the community wall, newest first.",
      "status": "active"
    },
    {
      "name": "get_deals",
      "rest_action": "deals",
      "description": "Get active AliExpress coupon codes.",
      "status": "active"
    },
    {
      "name": "generate_usecase",
      "rest_action": "generate_usecase",
      "description": "Generate a use case for a given topic: search skills, score, produce structured use case.",
      "status": "active"
    }
  ],
  "rate_limit": {
    "requests_per_minute": 60,
    "cleanup_interval_ms": 300000
  },
  "sanitize": {
    "query_max_len": 200,
    "slug_max_len": 80,
    "role_max_len": 50
  }
}
